tyba_cvxopt.libs/libsuitesparseconfig-5f9ba1c4.so.4.2.0
tyba_cvxopt.libs/libsatlas-c20ebb47.so.3.10
tyba_cvxopt.libs/libumfpack-225bb27f.so.5.6.1
tyba_cvxopt.libs/libcholmod-07e554e9.so.2.0.1
tyba_cvxopt.libs/libgfortran-8634ef04.so.3.0.0
tyba_cvxopt.libs/libcamd-97c7ceec.so.2.3.1
tyba_cvxopt.libs/libccolamd-5b90b5b4.so.2.8.0
tyba_cvxopt.libs/liblapack-29219182.so.3.4.2
tyba_cvxopt.libs/libamd-ed182fda.so.2.3.1
tyba_cvxopt.libs/libglpk-5a460381.so.40.3.1
tyba_cvxopt.libs/libblas-d36778f5.so.3.4.2
tyba_cvxopt.libs/libcolamd-65608a7e.so.2.8.0
cvxopt/lapack.cpython-38-aarch64-linux-gnu.so
cvxopt/misc.py
cvxopt/coneprog.py
cvxopt/cvxprog.py
cvxopt/base.cpython-38-aarch64-linux-gnu.so
cvxopt/__init__.py
cvxopt/glpk.cpython-38-aarch64-linux-gnu.so
cvxopt/msk.py
cvxopt/solvers.py
cvxopt/info.py
cvxopt/modeling.py
cvxopt/amd.cpython-38-aarch64-linux-gnu.so
cvxopt/_version.py
cvxopt/umfpack.cpython-38-aarch64-linux-gnu.so
cvxopt/printing.py
cvxopt/cholmod.cpython-38-aarch64-linux-gnu.so
cvxopt/blas.cpython-38-aarch64-linux-gnu.so
cvxopt/misc_solvers.cpython-38-aarch64-linux-gnu.so
tyba_cvxopt-1.3.1.dist-info/top_level.txt
tyba_cvxopt-1.3.1.dist-info/RECORD
tyba_cvxopt-1.3.1.dist-info/LICENSE
tyba_cvxopt-1.3.1.dist-info/METADATA
tyba_cvxopt-1.3.1.dist-info/WHEEL
