Metadata-Version: 2.1
Name: tyba-cvxopt
Version: 1.3.1
Summary: Convex optimization package
Home-page: http://cvxopt.org
Author: M. Andersen, J. Dahl, and L. Vandenberghe
Author-email: martin.skovgaard.andersen@gmail.com, dahl.joachim@gmail.com, vandenbe@ee.ucla.edu
License: GNU GPL version 3
Project-URL: Source, https://github.com/cvxopt/cvxopt
Classifier: Development Status :: 5 - Production/Stable
Classifier: Intended Audience :: Science/Research
Classifier: License :: OSI Approved :: GNU General Public License v3 (GPLv3)
Classifier: Operating System :: OS Independent
Classifier: Programming Language :: C
Classifier: Programming Language :: Python
Classifier: Programming Language :: Python :: 3
Classifier: Topic :: Scientific/Engineering
Requires-Python: >=2.7, !=3.0.*, !=3.1.*, !=3.2.*, !=3.3.*, !=3.4.*
License-File: LICENSE
